jdt/SwaggerConverter.py
jdt/__init__.py
jdt/capstatement2swagger.py
jdt/converter.py
jdt/csv2mongo.py
jdt/fhirbundle2mongo.py
jdt/fhirbundle2ndjson.py
jdt/fhirbundledownsize.py
jdt/fhirbundles2mongo.py
jdt/json2mongo.py
jdt/jsondir2ndjson.py
jdt/jsonlist2ndjson.py
jdt/ndjson2fhir.py
jdt/ndjson2mongo.py
jdt/ndjsonurl2fhir.py
jdt/ndjsonurl2mongo.py
jdt/sftp_ndjson2mongo.py
jdt/split_large_files.py
jdt-0.5.7.data/scripts/csv2mongo
jdt-0.5.7.data/scripts/fhirbundle2mongo
jdt-0.5.7.data/scripts/fhirbundle2ndjson
jdt-0.5.7.data/scripts/fhirbundledownsize
jdt-0.5.7.data/scripts/fhirbundles2mongo
jdt-0.5.7.data/scripts/json2mongo
jdt-0.5.7.data/scripts/jsondir2ndjson
jdt-0.5.7.data/scripts/jsonlist2ndjson
jdt-0.5.7.data/scripts/ndjson2fhir
jdt-0.5.7.data/scripts/ndjson2mongo
jdt-0.5.7.data/scripts/ndjsonurl2fhir
jdt-0.5.7.data/scripts/ndjsonurl2mongo
jdt-0.5.7.data/scripts/sftp_ndjson2mongo
jdt-0.5.7.data/scripts/split_large_files
jdt-0.5.7.dist-info/LICENSE
jdt-0.5.7.dist-info/METADATA
jdt-0.5.7.dist-info/WHEEL
jdt-0.5.7.dist-info/top_level.txt
jdt-0.5.7.dist-info/RECORD
