Metadata-Version: 2.1
Name: jdt
Version: 0.5.7
Summary: JSON Data Tools
Home-page: https://github.com/videntity/json-data-tools
Download-URL: https://gitbub.com/videntity/json-data-tools/tarball/master
Author: Alan Viars
Author-email: sales@videntity.com
License-File: LICENSE
Requires-Dist: pymongo
Requires-Dist: ndjson
Requires-Dist: requests
Requires-Dist: pysftp
